<?xml version='1.0'?>
<card xmlns='http://sourceforge.net/projects/firemox'
	xmlns:xsi='http://www.w3.org/2001/XMLSchema-instance'
	xsi:schemaLocation='http://sourceforge.net/projects/firemox ../../validator.xsd'
	name="Austere Command">
<rules-author-comment>riclas</rules-author-comment>

<!--
		4ww
	sorcery
	choose two - destroy all artifacts; or destroy all enchantments; or destroy all creatures with converted mana cost 3 or less; or destroy all creatures with converted mana cost 4 or greater.
 -->

	<init>
		<registers>
			<register index='white' value='2'/>
			<register index='colorless' value='4'/>
		</registers>
		<colors>white </colors>
		<idcards>sorcery </idcards>
	</init>
	<abilities>
		<activated-ability playable='this' name='' zone='hand'>
			<cost>
				<pay-mana value='manacost'/>
			</cost>
			<effects>
				<target type='card' mode='all' restriction-zone='play'>
					<test>
						<has-idcard idcard="artifact"/>
					</test>
				</target>
				<target type='card' mode='all' restriction-zone='play'>
					<test>
						<has-idcard idcard="enchantment"/>
					</test>
				</target>
				<action ref='destroy'/>
				<action ref='finish-spell'/>
			</effects>
		</activated-ability>
		<activated-ability playable='this' name='' zone='hand'>
			<cost>
				<pay-mana value='manacost'/>
			</cost>
			<effects>
				<target type='card' mode='all' restriction-zone='play'>
					<test>
						<has-idcard idcard="artifact"/>
					</test>
				</target>
				<target type='card' mode='all' restriction-zone='play'>
					<test>
						<and>
							<has-idcard idcard="creature"/>
							<sup-equal right="4">
								<left register="tested" index="manacost"/>
							</sup-equal>
						</and>
					</test>
				</target>
				<action ref='destroy'/>
				<action ref='finish-spell'/>
			</effects>
		</activated-ability>
		<activated-ability playable='this' name='' zone='hand'>
			<cost>
				<pay-mana value='manacost'/>
			</cost>
			<effects>
				<target type='card' mode='all' restriction-zone='play'>
					<test>
						<has-idcard idcard="artifact"/>
					</test>
				</target>
				<target type='card' mode='all' restriction-zone='play'>
					<test>
						<and>
							<has-idcard idcard="creature"/>
							<inf-equal right="3">
								<left register="tested" index="manacost"/>
							</inf-equal>
						</and>
					</test>
				</target>
				<action ref='destroy'/>
				<action ref='finish-spell'/>
			</effects>
		</activated-ability>
		<activated-ability playable='this' name='' zone='hand'>
			<cost>
				<pay-mana value='manacost'/>
			</cost>
			<effects>
				<target type='card' mode='all' restriction-zone='play'>
					<test>
						<has-idcard idcard="enchantment"/>
					</test>
				</target>
				<target type='card' mode='all' restriction-zone='play'>
					<test>
						<and>
							<has-idcard idcard="creature"/>
							<sup-equal right="4">
								<left register="tested" index="manacost"/>
							</sup-equal>
						</and>
					</test>
				</target>
				<action ref='destroy'/>
				<action ref='finish-spell'/>
			</effects>
		</activated-ability>
		<activated-ability playable='this' name='' zone='hand'>
			<cost>
				<pay-mana value='manacost'/>
			</cost>
			<effects>
				<target type='card' mode='all' restriction-zone='play'>
					<test>
						<has-idcard idcard="enchantment"/>
					</test>
				</target>
				<target type='card' mode='all' restriction-zone='play'>
					<test>
						<and>
							<has-idcard idcard="creature"/>
							<inf-equal right="3">
								<left register="tested" index="manacost"/>
							</inf-equal>
						</and>
					</test>
				</target>
				<action ref='destroy'/>
				<action ref='finish-spell'/>
			</effects>
		</activated-ability>
		<activated-ability playable='this' name='' zone='hand'>
			<cost>
				<pay-mana value='manacost'/>
			</cost>
			<effects>
				<target type='card' mode='all' restriction-zone='play'>
					<test>
						<and>
							<has-idcard idcard="creature"/>
							<sup-equal right="4">
								<left register="tested" index="manacost"/>
							</sup-equal>
						</and>
					</test>
				</target>
				<target type='card' mode='all' restriction-zone='play'>
					<test>
						<and>
							<has-idcard idcard="creature"/>
							<inf-equal right="3">
								<left register="tested" index="manacost"/>
							</inf-equal>
						</and>
					</test>
				</target>
				<action ref='destroy'/>
				<action ref='finish-spell'/>
			</effects>
		</activated-ability>
	</abilities>
</card>
