<?xml version='1.0'?>
<card xmlns='http://sourceforge.net/projects/firemox'
	xmlns:xsi='http://www.w3.org/2001/XMLSchema-instance'
	xsi:schemaLocation='http://sourceforge.net/projects/firemox ../../validator.xsd'
	name="Pyrostatic Pillar">
<rules-author-comment>riclas</rules-author-comment>

<!--
		1r
	enchantment
	whenever a player plays a spell with converted mana cost 3 or less, pyrostatic pillar deals 2 damage to that player.
 -->

	<init>
		<registers>
			<register index='red' value='1'/>
			<register index='colorless' value='1'/>
		</registers>
		<colors>red </colors>
		<idcards>global-enchantment </idcards>
	</init>
	<abilities>
		<ability ref='cast-spell'/>
		<triggered-ability zone='play'>
			<casting>
				<test>
					<inf-equal right="3">
						<left register="tested" index="manacost"/>
					</inf-equal>
				</test>
			</casting>	
			<effects>
				<target type="context.player"/>
				<assign-damage value='2' type='damage-normal'/>
			</effects>
		</triggered-ability>
	</abilities>
</card>
