<?xml version='1.0'?>
<card xmlns='http://sourceforge.net/projects/firemox'
	xmlns:xsi='http://www.w3.org/2001/XMLSchema-instance'
	xsi:schemaLocation='http://sourceforge.net/projects/firemox ../../validator.xsd'
	name="Shimmering Wings">
<rules-author-comment>riclas</rules-author-comment>

<!--
		u
	enchantment - aura
	enchant creature 
	enchanted creature has flying. 
	u: return shimmering wings to its owner's hand.
 -->

	<init>
		<registers>
			<register index='blue' value='1'/>
		</registers>
		<colors>blue </colors>
		<idcards>local-enchantment </idcards>
		<properties>aura </properties>
	</init>
	<abilities>
		<ability ref='cast-enchant'/>
		<activated-ability playable='instant' name='' zone='play'>
			<cost>
				<pay-mana blue='1' />
			</cost>
			<effects>
				<target type='this' />
				<action ref='return-to-hand'/>
			</effects>
		</activated-ability>
	</abilities>
	<attachment ref="flying"/>
</card>
