<?xml version="1.0"?>
<card xmlns="http://sourceforge.net/projects/firemox"
	xmlns:xsi="http://www.w3.org/2001/XMLSchema-instance"
	xsi:schemaLocation="http://sourceforge.net/projects/firemox ../../validator.xsd"
	name="Wild Growth">
	<rules-author-comment>Fabdouglas</rules-author-comment>

	<!--  {g} whenever enchanted land is tapped for mana, its controller adds {g} 
		to his or her mana pool. 
	-->
	<init>
		<registers>
			<register index="green" value="1" />
		</registers>
		<colors>green</colors>
		<idcards>local-enchantment</idcards>
	</init>
	<abilities>
		<triggered-ability zone="play" resolution="hidden">
			<become-tapped>
				<test>
					<is target="attachedto" />
				</test>
			</become-tapped>
			<effects>
				<create-ability>
					<save target="context.event-source" />
					<triggered-ability zone="play" optimize="choice">
						<given-mana color="nocare">
							<source-test>
								<is target="saved" />
							</source-test>
						</given-mana>
						<effects>
							<unregister-this />
							<give-mana green="1" to="attachedto.controller" />
						</effects>
					</triggered-ability>
					<until>
						<end-of-phase phase="nocare" />
					</until>
				</create-ability>
			</effects>
		</triggered-ability>
		<ability ref="cast-enchant" />
	</abilities>
	<attachment>
		<modifiers />
		<valid-target ref="valid-land-to-enchant" />
		<valid-attachment ref="valid-enchant-land" />
	</attachment>
</card>
